apitimewrapper/__init__.py
apitimewrapper/analysis.py
apitimewrapper/ms_wrap/__init__.py
apitimewrapper/ms_wrap/global_param.py
apitimewrapper/ms_wrap/hook_net.py
apitimewrapper/ms_wrap/my_print.py
apitimewrapper/ms_wrap/performance_cmp_new.py
apitimewrapper/ms_wrap/support_wrap_ops.yaml
apitimewrapper/ms_wrap/wrap_Tensor.py
apitimewrapper/ms_wrap/wrap_function.py
apitimewrapper/ms_wrap/wrap_nn.py
apitimewrapper/torch_wrap/__init__.py
apitimewrapper/torch_wrap/global_param.py
apitimewrapper/torch_wrap/hook_net.py
apitimewrapper/torch_wrap/my_print.py
apitimewrapper/torch_wrap/support_wrap_ops.yaml
apitimewrapper/torch_wrap/wrap_functional.py
apitimewrapper/torch_wrap/wrap_module.py
apitimewrapper/torch_wrap/wrap_tensor.py
apitimewrapper/torch_wrap/wrap_torch.py
apitimewrapper-0.0.7.dist-info/LICENSE
apitimewrapper-0.0.7.dist-info/METADATA
apitimewrapper-0.0.7.dist-info/WHEEL
apitimewrapper-0.0.7.dist-info/top_level.txt
apitimewrapper-0.0.7.dist-info/RECORD
