Metadata-Version: 2.1
Name: apitimewrapper
Version: 0.0.7
Summary: api time analysis
Home-page: https://www.mindspore.cn/
Author: fengyihang
Author-email: fengyihang1@huawei.com
License: Apache 2.0
Platform: UNKNOWN
License-File: LICENSE
